README.rst
setup.py
sherlok.py
sherlok.egg-info/PKG-INFO
sherlok.egg-info/SOURCES.txt
sherlok.egg-info/dependency_links.txt
sherlok.egg-info/top_level.txt