Metadata-Version: 1.1
Name: sherlok
Version: 0.1.4
Summary: A Python client for Sherlok
Home-page: https://github.com/renaud/sherlok-python
Author: Renaud Richardet
Author-email: renaud@apache.org
License: Apache License (2.0)
Keywords: distributed RESTful text mining
Platform: UNKNOWN
Classifier: Development Status :: 4 - Beta
Classifier: Intended Audience :: Developers
Classifier: Topic :: Software Development :: Build Tools
Classifier: License :: OSI Approved :: Apache Software License
Classifier: Programming Language :: Python :: 2.6
Classifier: Programming Language :: Python :: 2.7
